CHANGELOG
MANIFEST.in
README.md
ez_setup.py
setup.cfg
setup.py
tests/core_test.py
tests/core_test.pyc
tests/test_compat.py
tests/test_compat.pyc
tests/test_utils.py
tests/test_utils.pyc
tests/tvus_test.py
tests/tvus_test.pyc
tests/__pycache__/core_test.cpython-36.pyc
tests/__pycache__/test_compat.cpython-36.pyc
tests/__pycache__/test_utils.cpython-36.pyc
tests/__pycache__/tvus_test.cpython-36.pyc
tvu/__init__.py
tvu/_compat.py
tvu/_tvu.py
tvu/tvus.py
tvu.egg-info/PKG-INFO
tvu.egg-info/SOURCES.txt
tvu.egg-info/dependency_links.txt
tvu.egg-info/requires.txt
tvu.egg-info/top_level.txt
tvu.egg-info/zip-safe